airflow/providers/yandex/__init__.py
airflow/providers/yandex/get_provider_info.py
airflow/providers/yandex/version_compat.py
airflow/providers/yandex/hooks/__init__.py
airflow/providers/yandex/hooks/dataproc.py
airflow/providers/yandex/hooks/yandex.py
airflow/providers/yandex/hooks/yq.py
airflow/providers/yandex/links/__init__.py
airflow/providers/yandex/links/yq.py
airflow/providers/yandex/operators/__init__.py
airflow/providers/yandex/operators/dataproc.py
airflow/providers/yandex/operators/yq.py
airflow/providers/yandex/secrets/__init__.py
airflow/providers/yandex/secrets/lockbox.py
airflow/providers/yandex/utils/__init__.py
airflow/providers/yandex/utils/credentials.py
airflow/providers/yandex/utils/defaults.py
airflow/providers/yandex/utils/fields.py
airflow/providers/yandex/utils/user_agent.py
apache_airflow_providers_yandex-4.3.2.dist-info/entry_points.txt
apache_airflow_providers_yandex-4.3.2.dist-info/licenses/LICENSE
apache_airflow_providers_yandex-4.3.2.dist-info/licenses/NOTICE
apache_airflow_providers_yandex-4.3.2.dist-info/WHEEL
apache_airflow_providers_yandex-4.3.2.dist-info/METADATA
apache_airflow_providers_yandex-4.3.2.dist-info/RECORD
